{
  "version": 1,
  "author": "Mawin CK Channel",
  "editor": "wokwi",
  "parts": [
    { "type": "wokwi-arduino-uno", "id": "uno", "top": 0, "left": 0, "attrs": {} },
    {
      "type": "wokwi-led",
      "id": "led1",
      "top": -147.6,
      "left": 61.4,
      "attrs": { "color": "red" }
    },
    {
      "type": "wokwi-resistor",
      "id": "r1",
      "top": -62.4,
      "left": 57.05,
      "rotate": 90,
      "attrs": { "value": "133" }
    }
  ],
  "connections": [
    [ "r1:2", "uno:13", "green", [ "h0" ] ],
    [ "r1:1", "led1:A", "green", [ "h0" ] ],
    [ "led1:C", "uno:GND.1", "green", [ "v96", "h0.4" ] ]
  ],
  "dependencies": {}
}
